{
  "sprites": [
    {
      "id": 1,
      "fixed": true,
      "active": true,
      "x": 481,
      "y": 394,
      "seq": 33,
      "frame": 10,
      "type": 1,
      "size": 100,
      "script": "",
      "que": 600,
      "hard": 1,
      "clipleft": 0,
      "cliptop": 0,
      "clipright": 0,
      "clipbottom": 0,
      "warp": 0,
      "warpmap": 0,
      "warpx": 0,
      "warpy": 0,
      "nohit": 0
    },
    {
      "id": 2,
      "fixed": true,
      "active": true,
      "x": 386,
      "y": 258,
      "seq": 33,
      "frame": 9,
      "type": 1,
      "size": 100,
      "script": "",
      "que": 600,
      "hard": 1,
      "clipleft": 0,
      "cliptop": 0,
      "clipright": 0,
      "clipbottom": 0,
      "warp": 0,
      "warpmap": 0,
      "warpx": 0,
      "warpy": 0,
      "nohit": 1
    },
    {
      "id": 3,
      "fixed": true,
      "active": true,
      "x": 286,
      "y": 294,
      "seq": 33,
      "frame": 12,
      "type": 1,
      "size": 100,
      "script": "",
      "que": 600,
      "hard": 1,
      "clipleft": 0,
      "cliptop": 0,
      "clipright": 0,
      "clipbottom": 0,
      "warp": 0,
      "warpmap": 0,
      "warpx": 0,
      "warpy": 0,
      "nohit": 1
    },
    {
      "id": 4,
      "fixed": true,
      "active": true,
      "x": 186,
      "y": 345,
      "seq": 33,
      "frame": 12,
      "type": 1,
      "size": 100,
      "script": "",
      "que": 600,
      "hard": 1,
      "clipleft": 0,
      "cliptop": 0,
      "clipright": 0,
      "clipbottom": 0,
      "warp": 0,
      "warpmap": 0,
      "warpx": 0,
      "warpy": 0,
      "nohit": 1
    },
    {
      "id": 5,
      "fixed": true,
      "active": true,
      "x": 86,
      "y": 395,
      "seq": 33,
      "frame": 12,
      "type": 1,
      "size": 100,
      "script": "",
      "que": 600,
      "hard": 1,
      "clipleft": 0,
      "cliptop": 0,
      "clipright": 0,
      "clipbottom": 0,
      "warp": 0,
      "warpmap": 0,
      "warpx": 0,
      "warpy": 0,
      "nohit": 1
    },
    {
      "id": 6,
      "fixed": true,
      "active": true,
      "x": 460,
      "y": 239,
      "seq": 33,
      "frame": 8,
      "type": 1,
      "size": 100,
      "script": "",
      "que": 600,
      "hard": 1,
      "clipleft": 0,
      "cliptop": 0,
      "clipright": 0,
      "clipbottom": 0,
      "warp": 0,
      "warpmap": 0,
      "warpx": 0,
      "warpy": 0,
      "nohit": 1
    },
    {
      "id": 7,
      "fixed": true,
      "active": true,
      "x": 254,
      "y": 187,
      "seq": 32,
      "frame": 9,
      "type": 1,
      "size": 100,
      "script": "",
      "que": 199,
      "hard": 1,
      "clipleft": 0,
      "cliptop": 0,
      "clipright": 0,
      "clipbottom": 0,
      "warp": 0,
      "warpmap": 0,
      "warpx": 0,
      "warpy": 0,
      "nohit": 0
    }
  ]
}